LICENSE
MANIFEST.in
README.rst
setup.py
django_jquery_js.egg-info/PKG-INFO
django_jquery_js.egg-info/SOURCES.txt
django_jquery_js.egg-info/dependency_links.txt
django_jquery_js.egg-info/not-zip-safe
django_jquery_js.egg-info/requires.txt
django_jquery_js.egg-info/top_level.txt
jquery/__init__.py
jquery/context_processors.py
jquery/models.py
jquery/utils.py
jquery/static/js/jquery.js
jquery/static/js/jquery.min.js
jquery/templatetags/__init__.py
jquery/templatetags/jquery_tags.py