Metadata-Version: 1.1
Name: django-jquery-js
Version: 2.1.0
Summary: jQuery, bundled up so apps can depend upon it
Home-page: https://bitbucket.org/tim_heap/django-jquery
Author: Tim Heap
Author-email: tim@ionata.com.au
License: UNKNOWN
Platform: UNKNOWN
Classifier: Environment :: Web Environment
Classifier: Intended Audience :: Developers
Classifier: Operating System :: OS Independent
Classifier: Programming Language :: Python
Classifier: Framework :: Django
Classifier: License :: OSI Approved :: MIT License
